setup.py
rangeplus/__init__.py
rangeplus/rangeplus.py
rangeplus.egg-info/PKG-INFO
rangeplus.egg-info/SOURCES.txt
rangeplus.egg-info/dependency_links.txt
rangeplus.egg-info/top_level.txt
test/test_extra.py
test/test_range.py