Metadata-Version: 1.1
Name: rangeplus
Version: 0.5
Summary: Extended Python Range Class
Home-page: https://github.com/avnr/rangeplus
Author: Avner Herskovits
Author-email: avnr_ at outlook.com
License: UNKNOWN
Download-URL: https://github.com/avnr/rangeplus/tarball/0.5
Platform: UNKNOWN
Classifier: Development Status :: 4 - Beta
Classifier: Environment :: Other Environment
Classifier: Intended Audience :: Developers
Classifier: License :: OSI Approved :: MIT License
Classifier: Operating System :: OS Independent
Classifier: Programming Language :: Python
Classifier: Topic :: Software Development :: Libraries
